syft_awake/__init__.py
syft_awake/app.py
syft_awake/auto_install.py
syft_awake/client.py
syft_awake/discovery.py
syft_awake/models.py
syft_awake/syftbox_app/README.md
syft_awake/syftbox_app/run.sh
syft_awake-0.2.1.dist-info/METADATA
syft_awake-0.2.1.dist-info/WHEEL
syft_awake-0.2.1.dist-info/RECORD
