Metadata-Version: 2.4
Name: syft-awake
Version: 0.2.1
Summary: Fast, secure network awakeness monitoring for SyftBox - ping members to see who's online and ready for interactive queries
Project-URL: Homepage, https://github.com/iamtrask/syft-awake
Project-URL: Repository, https://github.com/iamtrask/syft-awake.git
Author-email: Andrew Trask <contact@andrewtrask.net>
License-Expression: Apache-2.0
Classifier: Development Status :: 3 - Alpha
Classifier: Intended Audience :: Developers
Classifier: License :: OSI Approved :: Apache Software License
Classifier: Programming Language :: Python :: 3
Classifier: Programming Language :: Python :: 3.12
Requires-Python: >=3.9
Requires-Dist: loguru>=0.7.0
Requires-Dist: pydantic>=2.0.0
Requires-Dist: pytest>=8.4.1
Requires-Dist: syft-core>=0.2.5
Requires-Dist: syft-event>=0.1.0
Requires-Dist: syft-rpc>=0.1.0
Requires-Dist: typing-extensions>=4.0.0
Provides-Extra: dev
Requires-Dist: pytest-cov>=4.1.0; extra == 'dev'
Requires-Dist: pytest>=7.0.0; extra == 'dev'
Requires-Dist: ruff>=0.3.0; extra == 'dev'
